<?xml version="1.0"?>
<opencv_storage>
<stage12>
  <maxWeakCount>5</maxWeakCount>
  <stageThreshold>-1.1559283733367920e+000</stageThreshold>
  <weakClassifiers>
    <_>
      <internalNodes>
        0 -1 9 -255078121 1314358034 -1877505770 -829254445 -516714493
        444852237 -267335423 -18431528</internalNodes>
      <leafValues>
        -7.1532845497131348e-001 4.2477875947952271e-001</leafValues></_>
    <_>
      <internalNodes>
        0 -1 33253 -1327877125 -427783385 -2080276261 -1610398906
        -1862203885 -1851551615 -901234682 -290301424</internalNodes>
      <leafValues>
        -7.9395949840545654e-001 3.9013731479644775e-001</leafValues></_>
    <_>
      <internalNodes>
        0 -1 30421 -1991173268 -532472127 -736949938 -321797477
        1074235801 1032491009 -324730771 -1578161479</internalNodes>
      <leafValues>
        -7.8784632682800293e-001 3.8439741730690002e-001</leafValues></_>
    <_>
      <internalNodes>
        0 -1 9112 -85989760 -921550768 1092816976 -1490820969 -884907255
        -1744732126 -108854622 -478959479</internalNodes>
      <leafValues>
        -5.2737104892730713e-001 6.8951147794723511e-001</leafValues></_>
    <_>
      <internalNodes>
        0 -1 30499 -1878156495 705823196 -2112797538 1812168906
        -259915464 -1165851507 -914288007 -1365607548</internalNodes>
      <leafValues>
        -7.1563917398452759e-001 4.8448017239570618e-001</leafValues></_></weakClassifiers></stage12>
</opencv_storage>
